clustalo.cpython-37m-darwin.so
clustalo-0.1.2.dist-info/LICENSE
clustalo-0.1.2.dist-info/METADATA
clustalo-0.1.2.dist-info/WHEEL
clustalo-0.1.2.dist-info/top_level.txt
clustalo-0.1.2.dist-info/RECORD
