Metadata-Version: 2.1
Name: clustalo
Version: 0.1.2
Summary: Python wrapper around libclustalo
Home-page: https://github.com/benchling/clustalo-python
Author: Benchling Engineering
Author-email: eng@benchling.com
License: UNKNOWN
Platform: UNKNOWN
